dataplay/__init__.py
dataplay/_nbdev.py
dataplay/corr.py
dataplay/geoms.py
dataplay/gifmap.py
dataplay/html.py
dataplay/intaker.py
dataplay/merge.py
dataplay-0.0.37.dist-info/LICENSE
dataplay-0.0.37.dist-info/METADATA
dataplay-0.0.37.dist-info/WHEEL
dataplay-0.0.37.dist-info/entry_points.txt
dataplay-0.0.37.dist-info/top_level.txt
dataplay-0.0.37.dist-info/RECORD
