Metadata-Version: 2.1
Name: dataplay
Version: 0.0.37
Summary: Code Tutorials
Home-page: https://github.com/bniajfi/dataplay
Author: Charles Karpati
Author-email: charles.karpati@gmail.com
License: MIT
Keywords: BNIA Baltimore
Platform: UNKNOWN
Classifier: Development Status :: 3 - Alpha
Classifier: Intended Audience :: Developers
Classifier: License :: OSI Approved :: MIT License
Classifier: Natural Language :: English
Classifier: Programming Language :: Python :: 3.6
Classifier: Programming Language :: Python :: 3.7
Classifier: Programming Language :: Python :: 3.8
Requires-Python: >=3.6
License-File: LICENSE
